robinhood/__init__.py
jc.robinhood-2.0.0.dist-info/LICENSE
jc.robinhood-2.0.0.dist-info/METADATA
jc.robinhood-2.0.0.dist-info/WHEEL
jc.robinhood-2.0.0.dist-info/top_level.txt
jc.robinhood-2.0.0.dist-info/RECORD
