Metadata-Version: 2.1
Name: jc.robinhood
Version: 2.0.0
Summary: Unofficial Robinhood API client library for Python
Home-page: https://github.com/jaredrcleghorn/robinhood
Author: Jared Cleghorn
Author-email: jaredrcleghorn@gmail.com
License: UNKNOWN
Platform: UNKNOWN
Classifier: Programming Language :: Python :: 3
Classifier: License :: OSI Approved :: MIT License
Classifier: Operating System :: OS Independent
Requires-Python: >=3.9
Requires-Dist: requests
